pelix_webconsole/__init__.py
pelix_webconsole/bundles.py
pelix_webconsole/core.py
pelix_webconsole/services.py
pelix_webconsole/utils.py
pelix_webconsole/_static/app.js
pelix_webconsole/_static/app.ts
pelix_webconsole/_static/dashboard.css
pelix_webconsole/_static/index.html
pelix_webconsole/_static/css/bootstrap-theme.css
pelix_webconsole/_static/css/bootstrap-theme.min.css
pelix_webconsole/_static/css/bootstrap.css
pelix_webconsole/_static/css/bootstrap.min.css
pelix_webconsole/_static/fonts/glyphicons-halflings-regular.eot
pelix_webconsole/_static/fonts/glyphicons-halflings-regular.svg
pelix_webconsole/_static/fonts/glyphicons-halflings-regular.ttf
pelix_webconsole/_static/fonts/glyphicons-halflings-regular.woff
pelix_webconsole/_static/fonts/glyphicons-halflings-regular.woff2
pelix_webconsole/_static/imgs/ipopo_logo.png
pelix_webconsole/_static/imgs/loading.gif
pelix_webconsole/_static/js/bootstrap.js
pelix_webconsole/_static/js/bootstrap.min.js
pelix_webconsole/_static/js/jquery.min.js
pelix_webconsole/_static/js/jquery.tablesorter.min.js
pelix_webconsole/_static/js/npm.js
pelix_webconsole/_static/typings/jquery.d.ts
pelix_webconsole-0.0.1.dist-info/DESCRIPTION.rst
pelix_webconsole-0.0.1.dist-info/METADATA
pelix_webconsole-0.0.1.dist-info/RECORD
pelix_webconsole-0.0.1.dist-info/WHEEL
pelix_webconsole-0.0.1.dist-info/metadata.json
pelix_webconsole-0.0.1.dist-info/top_level.txt
