Metadata-Version: 2.0
Name: pelix-webconsole
Version: 0.0.1
Summary: A Web Console for Pelix/iPOPO
Home-page: https://ipopo.coderxpress.net/
Author: Thomas Calmant
Author-email: thomas.calmant@gmail.com
License: Apache License 2.0
Platform: UNKNOWN
Classifier: Development Status :: 3 - Alpha
Classifier: Environment :: Web Environment
Classifier: Intended Audience :: Developers
Classifier: License :: OSI Approved :: Apache Software License
Classifier: Operating System :: OS Independent
Classifier: Programming Language :: Python :: 2.7
Classifier: Programming Language :: Python :: 3
Classifier: Programming Language :: Python :: 3.3
Classifier: Programming Language :: Python :: 3.4
Classifier: Programming Language :: Python :: 3.5
Requires-Dist: iPOPO (>=0.6.3)
Requires-Dist: setuptools
